wordle_aid.py
wordle_aid-2.9.dist-info/METADATA
wordle_aid-2.9.dist-info/WHEEL
wordle_aid-2.9.dist-info/entry_points.txt
wordle_aid-2.9.dist-info/top_level.txt
wordle_aid-2.9.dist-info/RECORD
