Metadata-Version: 2.4
Name: wordle-aid
Version: 2.9
Summary: CLI program to filter word choices to aid solving Wordle game problems
Author-email: Mark Blakeney <mark.blakeney@bullet-systems.net>
License-Expression: GPL-3.0-or-later
Project-URL: Homepage, https://github.com/bulletmark/wordle-aid
Keywords: wordle
Classifier: Programming Language :: Python :: 3
Requires-Python: >=3.8
Requires-Dist: pyspellchecker
Requires-Dist: argparse-from-file
Requires-Dist: importlib-metadata; python_version < "3.8"
